imageops/__init__.py
imageops/config.py
imageops/exceptions.py
imageops/core/__init__.py
imageops/core/processor.py
imageops/core/result.py
imageops/operations/__init__.py
imageops/operations/compress.py
imageops/operations/encode.py
imageops/operations/resize.py
imageops/operations/slice.py
imageops/providers/__init__.py
imageops/providers/anthropic.py
imageops/providers/base.py
imageops/providers/registry.py
imageops/strategies/__init__.py
imageops/strategies/sequential.py
imageops/utils/__init__.py
imageops/utils/cleanup.py
imageops/utils/download.py
imageops/utils/logging.py
imageops/utils/metadata.py
imageops/utils/validation.py
llm_imageops-1.1.0.dist-info/METADATA
llm_imageops-1.1.0.dist-info/WHEEL
llm_imageops-1.1.0.dist-info/top_level.txt
llm_imageops-1.1.0.dist-info/RECORD
