Metadata-Version: 2.4
Name: llm-imageops
Version: 1.1.0
Summary: Production-grade async image preprocessing for LLM APIs
Author: ImageOps Contributors
License: MIT
Project-URL: Homepage, https://pypi.org/project/llm-imageops/
Project-URL: Documentation, https://pypi.org/project/llm-imageops/
Keywords: llm,image-processing,anthropic,async,ai,agents,computer-vision
Classifier: Development Status :: 4 - Beta
Classifier: Intended Audience :: Developers
Classifier: License :: OSI Approved :: MIT License
Classifier: Programming Language :: Python :: 3.9
Classifier: Programming Language :: Python :: 3.10
Classifier: Programming Language :: Python :: 3.11
Classifier: Programming Language :: Python :: 3.12
Classifier: Programming Language :: Python :: 3.13
Classifier: Framework :: AsyncIO
Classifier: Topic :: Software Development :: Libraries
Classifier: Topic :: Scientific/Engineering :: Image Processing
Requires-Python: >=3.9
Requires-Dist: httpx>=0.28.0
Requires-Dist: aiofiles>=25.0.0
Requires-Dist: pydantic>=2.12.0
Requires-Dist: pydantic-settings>=2.12.0
Requires-Dist: opencv-python-headless>=4.12.0
Requires-Dist: pillow>=12.0.0
Requires-Dist: numpy>=2.2.0
Provides-Extra: dev
Requires-Dist: pytest>=7.4.0; extra == "dev"
Requires-Dist: pytest-asyncio>=0.21.0; extra == "dev"
Requires-Dist: pytest-cov>=4.1.0; extra == "dev"
Requires-Dist: black>=23.0.0; extra == "dev"
Requires-Dist: ruff>=0.1.0; extra == "dev"
Requires-Dist: mypy>=1.5.0; extra == "dev"
Dynamic: requires-python
